supercortex_fastapi_auth/__init__.py
supercortex_fastapi_auth/auth.py
supercortex_fastapi_auth/config.py
supercortex_fastapi_auth/utilities.py
supercortex_fastapi_auth-0.1.13.dist-info/METADATA
supercortex_fastapi_auth-0.1.13.dist-info/WHEEL
supercortex_fastapi_auth-0.1.13.dist-info/top_level.txt
supercortex_fastapi_auth-0.1.13.dist-info/RECORD
