Metadata-Version: 2.4
Name: supercortex-fastapi-auth
Version: 0.1.13
Summary: Authentication and authorization for FastAPI applications
Author-email: Isaac Harrison Gutekunst <isaac@supercortex.io>
License-Expression: MIT
Project-URL: Homepage, https://github.com/igutekunst/supercortex-auth
Project-URL: Bug Tracker, https://github.com/igutekunst/supercortex-auth/issues
Project-URL: Repository, https://github.com/igutekunst/supercortex-auth
Project-URL: Documentation, https://github.com/igutekunst/supercortex-auth#readme
Keywords: fastapi,authentication,authorization,jwt,supercortex
Classifier: Development Status :: 4 - Beta
Classifier: Intended Audience :: Developers
Classifier: Programming Language :: Python :: 3
Classifier: Programming Language :: Python :: 3.8
Classifier: Programming Language :: Python :: 3.9
Classifier: Programming Language :: Python :: 3.10
Classifier: Programming Language :: Python :: 3.11
Classifier: Programming Language :: Python :: 3.12
Classifier: Topic :: Software Development :: Libraries :: Application Frameworks
Classifier: Topic :: Internet :: WWW/HTTP :: HTTP Servers
Classifier: Topic :: Security
Requires-Python: >=3.8
Requires-Dist: fastapi>=0.68.0
Requires-Dist: pyjwt[crypto]>=2.1.0
Requires-Dist: httpx>=0.24.0
Requires-Dist: cryptography>=3.4.0
